<?xml version="1.0" encoding="utf-8"?>
<odoo>
    <data noupdate="1">

        <!--LOP Leave -->
        <!-- <record id="holiday_status_lwp" model="hr.holidays.status">
            <field name="name">Loss of Pay</field>
            <field name="code">LWP</field>
            <field name="limit" eval="True"/>
        </record>

        <record id="holiday_status_cll" model="hr.holidays.status">
            <field name="name">Casual Leave</field>
            <field name="code">CLL</field>
            <field name="limit" eval="True"/>
        </record>

        <record id="holiday_status_scl" model="hr.holidays.status">
            <field name="name">Special Casual Leave</field>
            <field name="code">SCL</field>
            <field name="limit" eval="True"/>
        </record>

        <record id="holiday_status_sl" model="hr.holidays.status">
            <field name="name">Sick Leave</field>
            <field name="code">SL</field>
            <field name="limit" eval="True"/>
        </record>

        <record id="holiday_status_pl" model="hr.holidays.status">
            <field name="name">Privilege Leave</field>
            <field name="code">PL</field>
            <field name="limit" eval="True"/>
        </record>

        <record id="holiday_status_mtl" model="hr.holidays.status">
            <field name="name">Maternity Leave</field>
            <field name="code">MTL</field>
            <field name="limit" eval="True"/>
        </record>

        <record id="holiday_status_ptl" model="hr.holidays.status">
            <field name="name">Paternity Leave</field>
            <field name="code">PTL</field>
            <field name="limit" eval="True"/>
        </record>

        <record id="holiday_status_coff" model="hr.holidays.status">
            <field name="name">Compensatory Off</field>
            <field name="code">COFF</field>
            <field name="limit" eval="True"/>
        </record> -->

    </data>
</odoo>
